odoo/addons/purchase_commercial_partner/README.rst
odoo/addons/purchase_commercial_partner/__init__.py
odoo/addons/purchase_commercial_partner/__manifest__.py
odoo/addons/purchase_commercial_partner/i18n/de.po
odoo/addons/purchase_commercial_partner/i18n/es.po
odoo/addons/purchase_commercial_partner/i18n/es_ES.po
odoo/addons/purchase_commercial_partner/i18n/es_PE.po
odoo/addons/purchase_commercial_partner/i18n/fr.po
odoo/addons/purchase_commercial_partner/i18n/fr_BE.po
odoo/addons/purchase_commercial_partner/i18n/gl.po
odoo/addons/purchase_commercial_partner/i18n/hr.po
odoo/addons/purchase_commercial_partner/i18n/it.po
odoo/addons/purchase_commercial_partner/i18n/nl.po
odoo/addons/purchase_commercial_partner/i18n/nl_NL.po
odoo/addons/purchase_commercial_partner/i18n/pt_BR.po
odoo/addons/purchase_commercial_partner/i18n/purchase_commercial_partner.pot
odoo/addons/purchase_commercial_partner/i18n/ro.po
odoo/addons/purchase_commercial_partner/i18n/sl.po
odoo/addons/purchase_commercial_partner/i18n/vi_VN.po
odoo/addons/purchase_commercial_partner/models/__init__.py
odoo/addons/purchase_commercial_partner/models/purchase.py
odoo/addons/purchase_commercial_partner/readme/CONTRIBUTORS.rst
odoo/addons/purchase_commercial_partner/readme/DESCRIPTION.rst
odoo/addons/purchase_commercial_partner/readme/USAGE.rst
odoo/addons/purchase_commercial_partner/static/description/icon.png
odoo/addons/purchase_commercial_partner/static/description/index.html
odoo/addons/purchase_commercial_partner/views/purchase_views.xml
odoo14_addon_purchase_commercial_partner-14.0.1.0.1.dev10.dist-info/METADATA
odoo14_addon_purchase_commercial_partner-14.0.1.0.1.dev10.dist-info/WHEEL
odoo14_addon_purchase_commercial_partner-14.0.1.0.1.dev10.dist-info/top_level.txt
odoo14_addon_purchase_commercial_partner-14.0.1.0.1.dev10.dist-info/RECORD
